mechanical_bull/__init__.py
mechanical_bull/actions/__init__.py
mechanical_bull/actions/accept_follow_request.py
mechanical_bull/actions/announce.py
mechanical_bull/actions/log_to_file.py
mechanical_bull/actions/reject_follow_request.py
mechanical_bull/actions/test_accept_reject_follow_request.py
mechanical_bull/actions/test_announce.py
mechanical_bull/add_user.py
mechanical_bull/amqp.py
mechanical_bull/event_loop.py
mechanical_bull/handlers.py
mechanical_bull/run.py
mechanical_bull/test_event_loop.py
mechanical_bull/test_handlers.py
mechanical_bull-0.2.6.dist-info/LICENSE
mechanical_bull-0.2.6.dist-info/METADATA
mechanical_bull-0.2.6.dist-info/WHEEL
mechanical_bull-0.2.6.dist-info/RECORD
