Metadata-Version: 2.1
Name: mechanical-bull
Version: 0.2.6
Summary: A framework to automate reacting to ActivityStreams events.
Home-page: https://codeberg.org/bovine/mechanical_bull
License: MIT
Author: Helge
Author-email: helge.krueger@gmail.com
Requires-Python: >=3.11,<4.0
Classifier: License :: OSI Approved :: MIT License
Classifier: Programming Language :: Python :: 3
Classifier: Programming Language :: Python :: 3.11
Requires-Dist: bovine (>=0.5.0,<0.6.0)
Requires-Dist: bovine-pubsub (>=0.5.0,<0.6.0)
Requires-Dist: tomli-w (>=1.0.0,<2.0.0)
Project-URL: Documentation, https://mechanical-bull.readthedocs.io/en/latest/
Project-URL: Repository, https://codeberg.org/bovine/mechanical_bull
